styml/__init__.py
styml-0.0.1.dist-info/LICENSE
styml-0.0.1.dist-info/METADATA
styml-0.0.1.dist-info/WHEEL
styml-0.0.1.dist-info/RECORD
